odoo/addons/website_event_contact/README.rst
odoo/addons/website_event_contact/__init__.py
odoo/addons/website_event_contact/__manifest__.py
odoo/addons/website_event_contact/i18n/de.po
odoo/addons/website_event_contact/i18n/es.po
odoo/addons/website_event_contact/i18n/it.po
odoo/addons/website_event_contact/i18n/website_event_contact.pot
odoo/addons/website_event_contact/readme/CONTRIBUTORS.md
odoo/addons/website_event_contact/readme/DESCRIPTION.md
odoo/addons/website_event_contact/readme/ROADMAP.md
odoo/addons/website_event_contact/readme/USAGE.md
odoo/addons/website_event_contact/static/description/icon.png
odoo/addons/website_event_contact/static/description/index.html
odoo/addons/website_event_contact/views/event_templates_page_registration.xml
odoo/addons/website_event_contact/views/snippets/snippets.xml
odoo_addon_website_event_contact-16.0.1.0.1.3.dist-info/METADATA
odoo_addon_website_event_contact-16.0.1.0.1.3.dist-info/WHEEL
odoo_addon_website_event_contact-16.0.1.0.1.3.dist-info/top_level.txt
odoo_addon_website_event_contact-16.0.1.0.1.3.dist-info/RECORD
