Metadata-Version: 2.1
Name: odoo-addon-website_event_contact
Version: 16.0.1.0.1.3
Summary: Display your event contacts on your event page
Home-page: https://github.com/OCA/event
Author: Moduon,OpenSynergy Indonesia,Odoo Community Association (OCA)
Author-email: support@odoo-community.org
License: AGPL-3
Classifier: Programming Language :: Python
Classifier: Framework :: Odoo
Classifier: Framework :: Odoo :: 16.0
Classifier: License :: OSI Approved :: GNU Affero General Public License v3
Requires-Python: >=3.10
Requires-Dist: odoo-addon-event-contact<16.1dev,>=16.0dev
Requires-Dist: odoo<16.1dev,>=16.0a
